python_compute_module/__init__.py
python_compute_module/api.py
python_compute_module/app.py
python_compute_module/query_runner.py
python_compute_module/read_connection_file.py
python_compute_module/schema.py
python_compute_module-0.2.0.dist-info/METADATA
python_compute_module-0.2.0.dist-info/WHEEL
python_compute_module-0.2.0.dist-info/RECORD
